{
    "/js/app.js": "/js/app.js",
    "/css/app.css": "/css/app.css",
    "/css/appLanding.css": "/css/appLanding.css",
    "/js/appLanding.js": "/js/appLanding.js",
    "/IdeaViewChunk.js": "/IdeaViewChunk.js",
    "/RetosChunk.js": "/RetosChunk.js",
    "/businessChunk.js": "/businessChunk.js",
    "/categoriesChunk.js": "/categoriesChunk.js",
    "/companyChunk.js": "/companyChunk.js",
    "/contactProfileChunk.js": "/contactProfileChunk.js",
    "/contactsChunk.js": "/contactsChunk.js",
    "/createContactChunk.js": "/createContactChunk.js",
    "/dashboardChunk.js": "/dashboardChunk.js",
    "/editContactChunk.js": "/editContactChunk.js",
    "/ideaComponentChunk.js": "/ideaComponentChunk.js",
    "/ideaCreationChunk.js": "/ideaCreationChunk.js",
    "/ideaEditChunk.js": "/ideaEditChunk.js",
    "/profileChunk.js": "/profileChunk.js",
    "/IdeaChunk.js": "/IdeaChunk.js",
    "/reportesChunk.js": "/reportesChunk.js",
    "/retosChunk.js": "/retosChunk.js",
    "/shareChunk.js": "/shareChunk.js",
    "/showRetoChunk.js": "/showRetoChunk.js",
    "/showRetoPublicoChunk.js": "/showRetoPublicoChunk.js",
    "/solucionChunk.js": "/solucionChunk.js",
    "/teamsChunk.js": "/teamsChunk.js"
}
